yapecs/__init__.py
yapecs/core.py
yapecs-0.4.0.dist-info/licenses/LICENSE
yapecs-0.4.0.dist-info/METADATA
yapecs-0.4.0.dist-info/WHEEL
yapecs-0.4.0.dist-info/top_level.txt
yapecs-0.4.0.dist-info/RECORD
