Metadata-Version: 2.4
Name: yapecs
Version: 0.4.0
Summary: Yet Another Python Experiment Configuration System (YAPECS)
Home-page: https://github.com/maxrmorrison/yapecs
Author: Max Morrison
Author-email: maxrmorrison@gmail.com
License: MIT
Keywords: configuration,config,experiment,manager
License-File: LICENSE
Requires-Dist: filelock
Dynamic: author
Dynamic: author-email
Dynamic: description
Dynamic: description-content-type
Dynamic: home-page
Dynamic: keywords
Dynamic: license
Dynamic: license-file
Dynamic: requires-dist
Dynamic: summary
